setup.py
ain/__init__.py
ain/ain.py
ain/env.development
ain/common/__init__.py
ain/common/constants.py
ain/common/util.py
ain/share/worker.env
ain/share/log/log.env
ain/worker/__init__.py
ain/worker/worker.py
ain/worker/manager/__init__.py
ain/worker/manager/docker.py
ain/worker/manager/ttyd.py
ain_worker_staging.egg-info/PKG-INFO
ain_worker_staging.egg-info/SOURCES.txt
ain_worker_staging.egg-info/dependency_links.txt
ain_worker_staging.egg-info/entry_points.txt
ain_worker_staging.egg-info/requires.txt
ain_worker_staging.egg-info/top_level.txt