Metadata-Version: 1.2
Name: ain-worker-staging
Version: 1.4.69
Summary: CLI of ain-worker-staging a Python script
Home-page: https://bitbucket.org/comcomai/ain-v1-worker
License: BSD
Platform: UNKNOWN
Classifier: License :: OSI Approved :: BSD License
Requires-Python: >=3
